sanitext/__init__.py
sanitext/cli.py
sanitext/emoji_set.py
sanitext/homoglyph_map.py
sanitext/text_sanitization.py
sanitext-0.1.1.dist-info/LICENSE
sanitext-0.1.1.dist-info/METADATA
sanitext-0.1.1.dist-info/WHEEL
sanitext-0.1.1.dist-info/entry_points.txt
sanitext-0.1.1.dist-info/RECORD
