Metadata-Version: 2.3
Name: sanitext
Version: 0.1.1
Summary: 
License: MIT
Author: panispani
Author-email: p.panayiotou2@gmail.com
Requires-Python: >=3.9,<4.0
Classifier: License :: OSI Approved :: MIT License
Classifier: Programming Language :: Python :: 3
Classifier: Programming Language :: Python :: 3.9
Classifier: Programming Language :: Python :: 3.10
Classifier: Programming Language :: Python :: 3.11
Classifier: Programming Language :: Python :: 3.12
Classifier: Programming Language :: Python :: 3.13
Requires-Dist: pyperclip (>=1.9.0,<2.0.0)
Requires-Dist: typer (>=0.15.2,<0.16.0)
Project-URL: Article, https://www.panispani.com/blog/2025/sanitext/
Project-URL: Repository, https://github.com/panispani/sanitext
